{"6uTRIyxZujtTdlRI9oP7LA==":"99-800x1200.jpg","kORbhg8tGCET4suaLkfAmQ==":"73c97149dde4810ff9669099ea53aa01-236x331.jpg","UprYmr77YsztfmFBWbmP/g==":"mbr-1920x1280.jpg","khvOvkzwZJ/98V57q2ZWtA==":"mbr-1-1920x1280.jpg","aYE9ZsyuQmLRZzr+S2z7mw==":"mbr-1920x1080.jpg","7aJqZ/jqllerQReW6SNf1g==":"1-556x949.jpg","h7baUgBS5v4E8w/nj8n1Pw==":"1-1-556x949.jpg","QFbNXrH8hoiwvJB7wfzB9g==":"1-2-556x949.jpg","rki7dWWKPTIQ7A5oXDnDyw==":"mbr-556x417.jpg","p2VZSyw3zEkLwWH6lJeRdg==":"mbr-1-556x417.jpg","O/SA0sxKa37cKWeGf9K9Sw==":"mbr-556x451.jpg","ubIlueYtH5Yiou4LfbDuJw==":"mbr-2-556x417.jpg","u+EsAHYpVZjieAHyXoMVRg==":"mbr-556x386.jpg","QODnmcw/d9Chnde60c4g5w==":"mbr-556x556.jpg","yZOds0rnZoILZHp85IqY1A==":"mbr-556x341.jpg","pH4lXSCqIvuJsebaXIxwXw==":"mbr-556x371.jpg","RVJVxbHn44zNoANtJV8rGg==":"mbr-3-556x417.jpg","5lF/WOZVzGX2aUwLmN5c0g==":"mbr-556x348.jpg","YGOCXlffP4eyVZxwqYVfTQ==":"mbr-556x370.jpg","dNr8+jMN5kQLJepzEMsFxQ==":"mbr-556x432.jpg","upVF0J0vE4xLGbgrdGo2/A==":"mbr-556x429.jpg","hEuhWjPvLvjy2IXRwa1Eeg==":"mbr-1-556x429.jpg","UXGva7MZAH8vgzGMLvVSyQ==":"mbr-556x397.jpg","YQ3G/j+Y7Zex5b0bTxihUw==":"mbr-2-556x429.jpg","srPJM+UZjb/Mx8NHBB0BBQ==":"mbr-556x260.jpg","fc1g9uMe7xkilaDZZ4H22w==":"mbr-1-556x397.jpg","M/uBoldgsXox5h2EqXKHCA==":"mbr-556x368.jpg","7acoRfNT6VQQHid9j6eQHw==":"mbr-1-556x371.jpg","lh4DHI97xo8+Tsl+Vk4EdQ==":"mbr-1-556x368.jpg","8agrq+tBqwA8FW2AtBD1aw==":"mbr-2-556x368.jpg","yoQDxzlNC5K4G0feLPF1yg==":"mbr-2-556x371.jpg","YYXOtJizLixzePuDUrNsHg==":"mbr-3-556x371.jpg","jdhIGW3TlRgK1LYgdwtlzw==":"mbr-556x312.jpg","g9nLIp1chg+3+E26Q+l8pQ==":"mbr-4-556x371.jpg","0O8HnOHf1JOUQcaH1K2lbQ==":"mbr-5-556x371.jpg","2ACZTgDVN6IQtQ1i9EU8ZQ==":"mbr-556x347.jpg","fctnEgsXm8xYsrXArb2hZA==":"mbr-556x517.jpg","EZB1fiC7KwoUxdgbhPsiXg==":"mbr-556x476.jpg","t1ywChgbZcvgydW7iVL/NA==":"01.jpg","spQJ+t4SRmhNfzzcdh3t5Q==":"01-1.jpg","dFyjc+6Fe6IBdsE1jfcA/g==":"mbr-6-556x371.jpg","yMj0nluU6/hpIDxTnSilBg==":"mbr-7-556x371.jpg","Ahh36JmmUGeCqIij4rRPxA==":"mbr-1920x1024.jpg","w3NRKdkflrkGymiSYWcKuA==":"mbr-2-1920x1280.jpg","kaWTN8ngT9Mma7biK4tRyA==":"mbr-1240x1920.jpg","Lqtqu/Cefh9yHyu5KXJMZQ==":"mbr-1580x1920.jpg","Kd2jCenY9zQ48M7N7ZT52A==":"mbr-3-1920x1280.jpg","3bzmDyrY3TJAzpfxh2Zl0Q==":"mbr-4-1920x1280.jpg","LRlla43Pv7j9OBhP55KnwA==":"mbr-1920x1275.jpg","056uSFctf+ceFMTc/Ndccg==":"mbr-5-1920x1280.jpg","CaOlq6c8ZEEPayiZSNyY7A==":"mbr-1920x1440.jpg","FQNciYnTw4h9zq2FftDVdw==":"mbr-1-1920x1065.jpg","rg0ybImDDXpwD7Z4DC/BTA==":"mbr-1-1920x1080.jpg","7TSXf2QUjmK+nHOjX/GEow==":"mbr-1920x1200.jpg","0gRHDw7b98Nc3GRv42jzXA==":"mbr-1-1920x1200.jpg","EB+Z6W2PsZFVBQtgyOQIOg==":"mbr-2-1920x1200.jpg","dPfGvyHZRD9Y/tBcuqO+VQ==":"mbr-1-1920x1440.jpg","Lg6pF7viCCHga52GxeJ4lw==":"mbr-2-1920x1440.jpg","Egv2dH0U4tXBpz4tEepjiw==":"mbr-6-1920x1280.jpg","Rz/LTkpBHNzC0mMT6IfPkw==":"mbr-556x313.jpg","hhAj7vQ5umxlPb60bMpvHA==":"mbr-556x360.jpg","AEnwaQ1dtLkTggj9VFA0cQ==":"mbr-1-556x370.jpg","kgM1NNSJdkiLK4iX02wTUg==":"mbr-2-556x370.jpg","4SCUfom1AIwWdh15Q7gLDg==":"mbr-7-1920x1280.jpg","0NFAei16f21SNCD1tuLsEQ==":"mbr-3-1920x1440.jpg","1XFAzLWFC+7pkdnji4P1Ng==":"mbr-420x236.jpg","IoBppll/He21Kw3XxC531Q==":"mbr-282x159.jpg","pkCRDQOA3yyHYnoNZknPPQ==":"mbr-1-282x159.jpg","xS/t26QBwpG9Qz8qCla7cQ==":"mbr-2-282x159.jpg","17gBFU3akTijmbgawj2HGg==":"mbr-278x156.jpg","3mqZzcB4D1u3ZFMpTBcyaw==":"mbr-1-278x156.jpg","JSTA10QV5vC0yjtyLl8eww==":"mbr-882x588.jpg","r7jAB3MyKv9o/7/WB4MpEg==":"mbr-882x392.jpg","zGzJ+PGGDyTJAZIO7lu8zw==":"mbr-1-882x588.jpg","v1K6Zxcj6VBYpkhBdlDH6Q==":"mbr-2-882x588.jpg","0wmlWsvW2XIHUlakmYAKQA==":"mbr-1-420x236.jpg","xOj3WIPT+sz94Acruvi/UQ==":"mbr-420x280.jpg","ZtMvuhel2S2cCqMUJEAffw==":"mbr-420x225.jpg","5S3y0penIh0EspK+g4ItOQ==":"mbr-420x271.jpg","UKfrWVr2yy8/wWrDEhNTRg==":"mbr-420x278.jpg","wUEsdxl1fnJ4L3YR933FYw==":"mbr-2-420x236.jpg","m9X6T7vI7EmGCUSA3Cn0EQ==":"background6.jpg","jh18mu9cM+qvaWQIwpZy4A==":"mbr-480x360.jpg","i/1PxnaF1DpjJdA4PC3gXA==":"mbr-1920x960.jpg","3F5Yi8v5fLQXK7mdlQzCRQ==":"mbr-1-1920x960.jpg","KlN9cDGO0rfjiJ5wvdWhDw==":"mbr-1920x1371.jpg","JWM2mTbb8/RZtBBxkgt9jQ==":"camerazoom-20190615192106584-482x271.jpg","fgJ1vtKignmdlGstmGD5Wg==":"camerazoom-20190615202329090-482x271.jpg","wKBaTJrSIWbZLE3lOjmPcg==":"camerazoom-20190615200013868-482x271.jpg","dnFGGx6vE4cbnnx+eRGZxw==":"camerazoom-20190615192059240-482x271.jpg","RvV2q4OEOSizEiaCf5wJ8w==":"camerazoom-20190615191430350-482x271.jpg","T8yNuBakiWUURhWMsAIImQ==":"img-20190612-wa0004-1032x581.jpg","CWnXLfxqyDyEmoC7KEWP5Q==":"img-20190612-wa0004-420x236.jpg","X9jL3uoirAgJE8cB+HhATw==":"img_20190617-181830-1924x3420.jpg","uDOeLKO4XurIcS+JTSo3EA==":"img_20190617-181831-1924x3420.jpg","xbg67V8kU5bPpLPODAu/6w==":"img_20190617-181832-1924x3420.jpg","fysPDPbDtZt1/2GlJcBxUg==":"img_20190617-181833-1924x3420.jpg","ghZp2TXy969u6hF8D/h7YQ==":"img_20190617-181830-642x1141.jpg","/iT1JzfA56d6GEpKqQEDMg==":"img_20190617-181831-642x1141.jpg","8/8TncmWYVlnx5A2eMaVpQ==":"img_20190617-181832-642x1141.jpg","D1xyzrLaK5X7wu0dp3Xtjg==":"img_20190617-181833-642x1141.jpg"}